gymcts/__init__.py
gymcts/colorful_console_utils.py
gymcts/gymcts_action_history_wrapper.py
gymcts/gymcts_agent.py
gymcts/gymcts_deepcopy_wrapper.py
gymcts/gymcts_distributed_agent.py
gymcts/gymcts_env_abc.py
gymcts/gymcts_neural_agent.py
gymcts/gymcts_node.py
gymcts/gymcts_tree_plotter.py
gymcts/logger.py
gymcts-1.4.5.dist-info/licenses/LICENSE
gymcts-1.4.5.dist-info/METADATA
gymcts-1.4.5.dist-info/WHEEL
gymcts-1.4.5.dist-info/top_level.txt
gymcts-1.4.5.dist-info/RECORD
