Metadata-Version: 2.4
Name: gymcts
Version: 1.4.5
Summary: A minimalistic implementation of the Monte Carlo Tree Search algorithm for planning problems fomulated as gymnaisum reinforcement learning environments.
Author: Alexander Nasuta
Author-email: Alexander Nasuta <alexander.nasuta@wzl-iqs.rwth-aachen.de>
License: MIT License
Project-URL: Homepage, https://github.com/Alexander-Nasuta/gymcts
Platform: unix
Platform: linux
Platform: osx
Platform: cygwin
Platform: win32
Classifier: License :: OSI Approved :: MIT License
Classifier: Programming Language :: Python
Classifier: Programming Language :: Python :: 3
Requires-Python: >=3.11
License-File: LICENSE
Requires-Dist: rich
Requires-Dist: numpy
Requires-Dist: gymnasium
Requires-Dist: matplotlib<3.9
Provides-Extra: examples
Requires-Dist: jsp-instance-utils; extra == "examples"
Requires-Dist: graph-matrix-jsp-env; extra == "examples"
Requires-Dist: graph-jsp-env; extra == "examples"
Provides-Extra: dev
Requires-Dist: jsp-instance-utils; extra == "dev"
Requires-Dist: graph-matrix-jsp-env>=0.3.0; extra == "dev"
Requires-Dist: graph-jsp-env; extra == "dev"
Requires-Dist: JSSEnv; extra == "dev"
Requires-Dist: pip-tools; extra == "dev"
Requires-Dist: pytest; extra == "dev"
Requires-Dist: pytest-cov; extra == "dev"
Requires-Dist: mypy; extra == "dev"
Requires-Dist: flake8; extra == "dev"
Requires-Dist: stable_baselines3; extra == "dev"
Requires-Dist: sphinx; extra == "dev"
Requires-Dist: myst-parser; extra == "dev"
Requires-Dist: sphinx-autobuild; extra == "dev"
Requires-Dist: sphinx-copybutton; extra == "dev"
Requires-Dist: furo; extra == "dev"
Requires-Dist: twine; extra == "dev"
Requires-Dist: sphinx-copybutton; extra == "dev"
Requires-Dist: nbsphinx; extra == "dev"
Requires-Dist: pandoc; extra == "dev"
Requires-Dist: jupytext; extra == "dev"
Requires-Dist: jupyter; extra == "dev"
Requires-Dist: typing_extensions>=4.12.0; extra == "dev"
Dynamic: license-file
